swagger_client/__init__.py
swagger_client/api_client.py
swagger_client/configuration.py
swagger_client/rest.py
swagger_client/api/__init__.py
swagger_client/api/actions_api.py
swagger_client/api/backup_api.py
swagger_client/api/backups_api.py
swagger_client/api/bdbs_api.py
swagger_client/api/cluster_api.py
swagger_client/api/crdbs_api.py
swagger_client/api/default_api.py
swagger_client/api/shards_api.py
swagger_client/api/users_api.py
swagger_client/models/__init__.py
swagger_client/models/action.py
swagger_client/models/action_cluster.py
swagger_client/models/action_cluster_change_master.py
swagger_client/models/action_node.py
swagger_client/models/action_node_clone_node_settings.py
swagger_client/models/action_node_enslave_node.py
swagger_client/models/action_node_maintenance_off.py
swagger_client/models/action_node_maintenance_on.py
swagger_client/models/actions_export_body.py
swagger_client/models/actions_import_body.py
swagger_client/models/actions_recover_body.py
swagger_client/models/alert_settings_with_threshold.py
swagger_client/models/all_ofactions_export_body_export_location.py
swagger_client/models/all_ofbdb_crdt_sources.py
swagger_client/models/all_ofbdb_crdt_sync.py
swagger_client/models/all_ofbdb_import_failure_reason.py
swagger_client/models/all_ofbdb_replica_sources.py
swagger_client/models/all_ofbdb_replica_sync.py
swagger_client/models/all_ofbdb_snapshot_policy.py
swagger_client/models/all_ofbdb_sync.py
swagger_client/models/all_ofcluster_alert_settings_cluster_certs_about_to_expire.py
swagger_client/models/all_ofcluster_alert_settings_node_cpu_utilization.py
swagger_client/models/all_ofcluster_alert_settings_node_ephemeral_storage.py
swagger_client/models/all_ofcluster_alert_settings_node_free_flash.py
swagger_client/models/all_ofcluster_alert_settings_node_internal_certs_about_to_expire.py
swagger_client/models/all_ofcluster_alert_settings_node_memory.py
swagger_client/models/all_ofcluster_alert_settings_node_net_throughput.py
redis_enterprise_python-1.0.3.dist-info/METADATA
redis_enterprise_python-1.0.3.dist-info/WHEEL
redis_enterprise_python-1.0.3.dist-info/top_level.txt
redis_enterprise_python-1.0.3.dist-info/RECORD
