Metadata-Version: 2.1
Name: redis-enterprise-python
Version: 1.0.3
Summary: Redis Enterprise API
Home-page: UNKNOWN
Author-email: matthew.royal@redis.com
License: UNKNOWN
Keywords: Swagger,Redis Enterprise API,Redis Enterprise,Redis
Platform: UNKNOWN
Requires-Dist: urllib3 (>=1.15)
Requires-Dist: six (>=1.10)
Requires-Dist: certifi
Requires-Dist: python-dateutil
